multi_request/__init__.py
multi_request/mreq.py
multi_request-0.0.9.dist-info/METADATA
multi_request-0.0.9.dist-info/WHEEL
multi_request-0.0.9.dist-info/top_level.txt
multi_request-0.0.9.dist-info/RECORD
