Metadata-Version: 2.1
Name: multi-request
Version: 0.0.9
Summary: UNKNOWN
Home-page: UNKNOWN
Author: Zhao Xu
License: UNKNOWN
Platform: UNKNOWN
Classifier: Environment :: Console
Classifier: Intended Audience :: Developers
Classifier: Programming Language :: Python
Requires-Dist: pandas (==1.3.4)
Requires-Dist: requests (==2.26.0)
